myfabric/__init__.py
myfabric/__version__.py
myfabric/install.sh
myfabric/install_runner.py
myfabric/main.py
myfabric/uninstall.sh
myfabric_connector-0.2.32.dist-info/METADATA
myfabric_connector-0.2.32.dist-info/WHEEL
myfabric_connector-0.2.32.dist-info/entry_points.txt
myfabric_connector-0.2.32.dist-info/top_level.txt
myfabric_connector-0.2.32.dist-info/RECORD
