Metadata-Version: 2.1
Name: myfabric-connector
Version: 0.2.32
Summary: Программа для взаимодействия 3D принтеров и  CRM MyFabric
Home-page: https://github.com/myfabric-ru/ws-connector
Author: Khonik
Author-email: khonikdev@gmail.com
Classifier: Programming Language :: Python :: 3
Requires-Dist: pathlib2
Requires-Dist: websocket-client
Requires-Dist: requests
Requires-Dist: pysher-khonik ==1.0.12
